[
  {
    "ID": 567891,
    "ReportID": 17620,
    "AssetTemplateID": 164,
    "Name": "Air Conditioning - Packaged Unit",
    "Area": 1,
    "IsGivenCost": "0",
    "RateFormula": "150",
    "QuantityFormula": "680+60+85",
    "InstallationDateFormula": "cc",
    "ScrappedDateFormula": null,
    "IsDivision43Deduction": "1",
    "HundredPercentOption": 0,
    "NumberOfItems": 1,
    "CanHundredPercent": "0",
    "ExcludeExpenditure": "0",
    "ExcludeFees": "0"
  },
  {
    "ID": 567893,
    "ReportID": 17620,
    "AssetTemplateID": 171,
    "Name": "Automatic Garage Door - Motors",
    "Area": 1,
    "IsGivenCost": "0",
    "RateFormula": "6000",
    "QuantityFormula": "1",
    "InstallationDateFormula": "cc",
    "ScrappedDateFormula": null,
    "IsDivision43Deduction": "1",
    "HundredPercentOption": 0,
    "NumberOfItems": 2,
    "CanHundredPercent": "0",
    "ExcludeExpenditure": "0",
    "ExcludeFees": "0"
  },
  {
    "ID": 567894,
    "ReportID": 17620,
    "AssetTemplateID": 176,
    "Name": "Bathroom Accessories - Freestanding",
    "Area": 1,
    "IsGivenCost": "0",
    "RateFormula": "270",
    "QuantityFormula": "2",
    "InstallationDateFormula": "cc",
    "ScrappedDateFormula": null,
    "IsDivision43Deduction": "1",
    "HundredPercentOption": 0,
    "NumberOfItems": 1,
    "CanHundredPercent": "0",
    "ExcludeExpenditure": "0",
    "ExcludeFees": "0"
  },
  {
    "ID": 567895,
    "ReportID": 17620,
    "AssetTemplateID": 175,
    "Name": "Barbecues - Sliding Trays & Cookers",
    "Area": 1,
    "IsGivenCost": "0",
    "RateFormula": "4500",
    "QuantityFormula": "2",
    "InstallationDateFormula": "cc",
    "ScrappedDateFormula": null,
    "IsDivision43Deduction": "1",
    "HundredPercentOption": 0,
    "NumberOfItems": 1,
    "CanHundredPercent": "0",
    "ExcludeExpenditure": "0",
    "ExcludeFees": "0"
  },
  {
    "ID": 567896,
    "ReportID": 17620,
    "AssetTemplateID": 180,
    "Name": "Carpet",
    "Area": 1,
    "IsGivenCost": "0",
    "RateFormula": "105",
    "QuantityFormula": "680",
    "InstallationDateFormula": "cc",
    "ScrappedDateFormula": null,
    "IsDivision43Deduction": "1",
    "HundredPercentOption": 0,
    "NumberOfItems": 1,
    "CanHundredPercent": "0",
    "ExcludeExpenditure": "0",
    "ExcludeFees": "0"
  },
  {
    "ID": 567897,
    "ReportID": 17620,
    "AssetTemplateID": 184,
    "Name": "Closed Circuit Television - Cameras & Monitors",
    "Area": 1,
    "IsGivenCost": "0",
    "RateFormula": "550",
    "QuantityFormula": "18",
    "InstallationDateFormula": "cc",
    "ScrappedDateFormula": null,
    "IsDivision43Deduction": "1",
    "HundredPercentOption": 0,
    "NumberOfItems": 1,
    "CanHundredPercent": "0",
    "ExcludeExpenditure": "0",
    "ExcludeFees": "0"
  },
  {
    "ID": 567898,
    "ReportID": 17620,
    "AssetTemplateID": 185,
    "Name": "Closed Circuit Television - Digital Recorders",
    "Area": 1,
    "IsGivenCost": "0",
    "RateFormula": "12000",
    "QuantityFormula": "1",
    "InstallationDateFormula": "cc",
    "ScrappedDateFormula": null,
    "IsDivision43Deduction": "1",
    "HundredPercentOption": 0,
    "NumberOfItems": 1,
    "CanHundredPercent": "0",
    "ExcludeExpenditure": "0",
    "ExcludeFees": "0"
  },
  {
    "ID": 567899,
    "ReportID": 17620,
    "AssetTemplateID": 198,
    "Name": "Door Closers",
    "Area": 1,
    "IsGivenCost": "0",
    "RateFormula": "700",
    "QuantityFormula": "18",
    "InstallationDateFormula": "cc",
    "ScrappedDateFormula": null,
    "IsDivision43Deduction": "1",
    "HundredPercentOption": 0,
    "NumberOfItems": 1,
    "CanHundredPercent": "0",
    "ExcludeExpenditure": "0",
    "ExcludeFees": "0"
  },
  {
    "ID": 567900,
    "ReportID": 17620,
    "AssetTemplateID": 201,
    "Name": "Emergency Warning & Intercommunication Systems",
    "Area": 1,
    "IsGivenCost": "0",
    "RateFormula": "5500",
    "QuantityFormula": "9",
    "InstallationDateFormula": "cc",
    "ScrappedDateFormula": null,
    "IsDivision43Deduction": "1",
    "HundredPercentOption": 0,
    "NumberOfItems": 1,
    "CanHundredPercent": "0",
    "ExcludeExpenditure": "0",
    "ExcludeFees": "0"
  },
  {
    "ID": 567901,
    "ReportID": 17620,
    "AssetTemplateID": 204,
    "Name": "Fire Alarm Bells",
    "Area": 1,
    "IsGivenCost": "0",
    "RateFormula": "2500",
    "QuantityFormula": "9",
    "InstallationDateFormula": "cc",
    "ScrappedDateFormula": null,
    "IsDivision43Deduction": "1",
    "HundredPercentOption": 0,
    "NumberOfItems": 1,
    "CanHundredPercent": "0",
    "ExcludeExpenditure": "0",
    "ExcludeFees": "0"
  },
  {
    "ID": 567902,
    "ReportID": 17620,
    "AssetTemplateID": 205,
    "Name": "Fire Booster Pumps",
    "Area": 1,
    "IsGivenCost": "0",
    "RateFormula": "15000",
    "QuantityFormula": "9",
    "InstallationDateFormula": "cc",
    "ScrappedDateFormula": null,
    "IsDivision43Deduction": "1",
    "HundredPercentOption": 0,
    "NumberOfItems": 1,
    "CanHundredPercent": "0",
    "ExcludeExpenditure": "0",
    "ExcludeFees": "0"
  },
  {
    "ID": 567903,
    "ReportID": 17620,
    "AssetTemplateID": 206,
    "Name": "Fire Detection Alarms",
    "Area": 1,
    "IsGivenCost": "0",
    "RateFormula": "3500",
    "QuantityFormula": "9",
    "InstallationDateFormula": "cc",
    "ScrappedDateFormula": null,
    "IsDivision43Deduction": "1",
    "HundredPercentOption": 0,
    "NumberOfItems": 1,
    "CanHundredPercent": "0",
    "ExcludeExpenditure": "0",
    "ExcludeFees": "0"
  },
  {
    "ID": 567904,
    "ReportID": 17620,
    "AssetTemplateID": 207,
    "Name": "Fire Extinguishers",
    "Area": 1,
    "IsGivenCost": "0",
    "RateFormula": "900",
    "QuantityFormula": "18",
    "InstallationDateFormula": "cc",
    "ScrappedDateFormula": null,
    "IsDivision43Deduction": "1",
    "HundredPercentOption": 0,
    "NumberOfItems": 1,
    "CanHundredPercent": "0",
    "ExcludeExpenditure": "0",
    "ExcludeFees": "0"
  },
  {
    "ID": 567905,
    "ReportID": 17620,
    "AssetTemplateID": 208,
    "Name": "Fire Hoses & Nozzles",
    "Area": 1,
    "IsGivenCost": "0",
    "RateFormula": "1350",
    "QuantityFormula": "9",
    "InstallationDateFormula": "cc",
    "ScrappedDateFormula": null,
    "IsDivision43Deduction": "1",
    "HundredPercentOption": 0,
    "NumberOfItems": 1,
    "CanHundredPercent": "0",
    "ExcludeExpenditure": "0",
    "ExcludeFees": "0"
  },
  {
    "ID": 567906,
    "ReportID": 17620,
    "AssetTemplateID": 209,
    "Name": "Fire Indicator Panels",
    "Area": 1,
    "IsGivenCost": "0",
    "RateFormula": "12500",
    "QuantityFormula": "9",
    "InstallationDateFormula": "cc",
    "ScrappedDateFormula": null,
    "IsDivision43Deduction": "1",
    "HundredPercentOption": 0,
    "NumberOfItems": 1,
    "CanHundredPercent": "0",
    "ExcludeExpenditure": "0",
    "ExcludeFees": "0"
  },
  {
    "ID": 567907,
    "ReportID": 17620,
    "AssetTemplateID": 212,
    "Name": "Furniture - Freestanding",
    "Area": 1,
    "IsGivenCost": "0",
    "RateFormula": "45000",
    "QuantityFormula": "1",
    "InstallationDateFormula": "cc",
    "ScrappedDateFormula": null,
    "IsDivision43Deduction": "1",
    "HundredPercentOption": 0,
    "NumberOfItems": 10,
    "CanHundredPercent": "0",
    "ExcludeExpenditure": "0",
    "ExcludeFees": "0"
  },
  {
    "ID": 567908,
    "ReportID": 17620,
    "AssetTemplateID": 215,
    "Name": "Furniture - Outdoor",
    "Area": 1,
    "IsGivenCost": "0",
    "RateFormula": "30000",
    "QuantityFormula": "1",
    "InstallationDateFormula": "cc",
    "ScrappedDateFormula": null,
    "IsDivision43Deduction": "1",
    "HundredPercentOption": 0,
    "NumberOfItems": 10,
    "CanHundredPercent": "0",
    "ExcludeExpenditure": "0",
    "ExcludeFees": "0"
  },
  {
    "ID": 567909,
    "ReportID": 17620,
    "AssetTemplateID": 218,
    "Name": "Garbage Bins",
    "Area": 1,
    "IsGivenCost": "0",
    "RateFormula": "99",
    "QuantityFormula": "32*2",
    "InstallationDateFormula": "cc",
    "ScrappedDateFormula": null,
    "IsDivision43Deduction": "1",
    "HundredPercentOption": 0,
    "NumberOfItems": 3,
    "CanHundredPercent": "0",
    "ExcludeExpenditure": "0",
    "ExcludeFees": "0"
  },
  {
    "ID": 567910,
    "ReportID": 17620,
    "AssetTemplateID": 222,
    "Name": "Gardening Watering Installations",
    "Area": 1,
    "IsGivenCost": "0",
    "RateFormula": "5000",
    "QuantityFormula": "1",
    "InstallationDateFormula": "cc",
    "ScrappedDateFormula": null,
    "IsDivision43Deduction": "1",
    "HundredPercentOption": 0,
    "NumberOfItems": 1,
    "CanHundredPercent": "0",
    "ExcludeExpenditure": "0",
    "ExcludeFees": "0"
  },
  {
    "ID": 567911,
    "ReportID": 17620,
    "AssetTemplateID": 224,
    "Name": "Gym Asset - Cardiovascular",
    "Area": 1,
    "IsGivenCost": "0",
    "RateFormula": "4000",
    "QuantityFormula": "8",
    "InstallationDateFormula": "cc",
    "ScrappedDateFormula": null,
    "IsDivision43Deduction": "1",
    "HundredPercentOption": 0,
    "NumberOfItems": 10,
    "CanHundredPercent": "0",
    "ExcludeExpenditure": "0",
    "ExcludeFees": "0"
  },
  {
    "ID": 567912,
    "ReportID": 17620,
    "AssetTemplateID": 225,
    "Name": "Gym Asset - Resistance",
    "Area": 1,
    "IsGivenCost": "0",
    "RateFormula": "2500",
    "QuantityFormula": "5",
    "InstallationDateFormula": "cc",
    "ScrappedDateFormula": null,
    "IsDivision43Deduction": "1",
    "HundredPercentOption": 0,
    "NumberOfItems": 10,
    "CanHundredPercent": "0",
    "ExcludeExpenditure": "0",
    "ExcludeFees": "0"
  },
  {
    "ID": 567913,
    "ReportID": 17620,
    "AssetTemplateID": 234,
    "Name": "Hot Water Systems",
    "Area": 1,
    "IsGivenCost": "0",
    "RateFormula": "1550",
    "QuantityFormula": "32",
    "InstallationDateFormula": "cc",
    "ScrappedDateFormula": null,
    "IsDivision43Deduction": "1",
    "HundredPercentOption": 0,
    "NumberOfItems": 1,
    "CanHundredPercent": "0",
    "ExcludeExpenditure": "0",
    "ExcludeFees": "0"
  },
  {
    "ID": 567914,
    "ReportID": 17620,
    "AssetTemplateID": 236,
    "Name": "Intercom System Assets",
    "Area": 1,
    "IsGivenCost": "0",
    "RateFormula": "850",
    "QuantityFormula": "32",
    "InstallationDateFormula": "cc",
    "ScrappedDateFormula": null,
    "IsDivision43Deduction": "1",
    "HundredPercentOption": 0,
    "NumberOfItems": 1,
    "CanHundredPercent": "0",
    "ExcludeExpenditure": "0",
    "ExcludeFees": "0"
  },
  {
    "ID": 567915,
    "ReportID": 17620,
    "AssetTemplateID": 241,
    "Name": "Lifts",
    "Area": 1,
    "IsGivenCost": "0",
    "RateFormula": "150000",
    "QuantityFormula": "1",
    "InstallationDateFormula": "cc",
    "ScrappedDateFormula": null,
    "IsDivision43Deduction": "1",
    "HundredPercentOption": 0,
    "NumberOfItems": 1,
    "CanHundredPercent": "0",
    "ExcludeExpenditure": "0",
    "ExcludeFees": "0"
  },
  {
    "ID": 567916,
    "ReportID": 17620,
    "AssetTemplateID": 243,
    "Name": "Light Shades",
    "Area": 1,
    "IsGivenCost": "0",
    "RateFormula": "60",
    "QuantityFormula": "75",
    "InstallationDateFormula": "cc",
    "ScrappedDateFormula": null,
    "IsDivision43Deduction": "1",
    "HundredPercentOption": 0,
    "NumberOfItems": 10,
    "CanHundredPercent": "0",
    "ExcludeExpenditure": "0",
    "ExcludeFees": "0"
  },
  {
    "ID": 567917,
    "ReportID": 17620,
    "AssetTemplateID": 246,
    "Name": "MATV System",
    "Area": 1,
    "IsGivenCost": "0",
    "RateFormula": "250",
    "QuantityFormula": "32",
    "InstallationDateFormula": "cc",
    "ScrappedDateFormula": null,
    "IsDivision43Deduction": "1",
    "HundredPercentOption": 0,
    "NumberOfItems": 1,
    "CanHundredPercent": "0",
    "ExcludeExpenditure": "0",
    "ExcludeFees": "0"
  },
  {
    "ID": 567918,
    "ReportID": 17620,
    "AssetTemplateID": 254,
    "Name": "Pumps",
    "Area": 1,
    "IsGivenCost": "0",
    "RateFormula": "3250",
    "QuantityFormula": "2",
    "InstallationDateFormula": "cc",
    "ScrappedDateFormula": null,
    "IsDivision43Deduction": "1",
    "HundredPercentOption": 0,
    "NumberOfItems": 1,
    "CanHundredPercent": "0",
    "ExcludeExpenditure": "0",
    "ExcludeFees": "0"
  },
  {
    "ID": 567919,
    "ReportID": 17620,
    "AssetTemplateID": 260,
    "Name": "Security Monitoring Door Controllers & Code Pads",
    "Area": 1,
    "IsGivenCost": "0",
    "RateFormula": "185",
    "QuantityFormula": "32",
    "InstallationDateFormula": "cc",
    "ScrappedDateFormula": null,
    "IsDivision43Deduction": "1",
    "HundredPercentOption": 0,
    "NumberOfItems": 1,
    "CanHundredPercent": "0",
    "ExcludeExpenditure": "0",
    "ExcludeFees": "0"
  },
  {
    "ID": 567920,
    "ReportID": 17620,
    "AssetTemplateID": 261,
    "Name": "Security Monitoring Proximity Readers",
    "Area": 1,
    "IsGivenCost": "0",
    "RateFormula": "165",
    "QuantityFormula": "32",
    "InstallationDateFormula": "cc",
    "ScrappedDateFormula": null,
    "IsDivision43Deduction": "1",
    "HundredPercentOption": 0,
    "NumberOfItems": 1,
    "CanHundredPercent": "0",
    "ExcludeExpenditure": "0",
    "ExcludeFees": "0"
  },
  {
    "ID": 567922,
    "ReportID": 17620,
    "AssetTemplateID": 270,
    "Name": "Stair Pressurisation Assets",
    "Area": 1,
    "IsGivenCost": "0",
    "RateFormula": "7500",
    "QuantityFormula": "9",
    "InstallationDateFormula": "cc",
    "ScrappedDateFormula": null,
    "IsDivision43Deduction": "1",
    "HundredPercentOption": 0,
    "NumberOfItems": 1,
    "CanHundredPercent": "0",
    "ExcludeExpenditure": "0",
    "ExcludeFees": "0"
  },
  {
    "ID": 567923,
    "ReportID": 17620,
    "AssetTemplateID": 274,
    "Name": "Swimming Pool - Cleaners",
    "Area": 1,
    "IsGivenCost": "0",
    "RateFormula": "6500",
    "QuantityFormula": "1",
    "InstallationDateFormula": "cc",
    "ScrappedDateFormula": null,
    "IsDivision43Deduction": "1",
    "HundredPercentOption": 0,
    "NumberOfItems": 1,
    "CanHundredPercent": "0",
    "ExcludeExpenditure": "0",
    "ExcludeFees": "0"
  },
  {
    "ID": 567924,
    "ReportID": 17620,
    "AssetTemplateID": 275,
    "Name": "Swimming Pool & Spa - Filtration & Chlorinators",
    "Area": 1,
    "IsGivenCost": "0",
    "RateFormula": "10000",
    "QuantityFormula": "1",
    "InstallationDateFormula": "cc",
    "ScrappedDateFormula": null,
    "IsDivision43Deduction": "1",
    "HundredPercentOption": 0,
    "NumberOfItems": 1,
    "CanHundredPercent": "0",
    "ExcludeExpenditure": "0",
    "ExcludeFees": "0"
  },
  {
    "ID": 567925,
    "ReportID": 17620,
    "AssetTemplateID": 285,
    "Name": "Ventilation Fans",
    "Area": 1,
    "IsGivenCost": "0",
    "RateFormula": "15",
    "QuantityFormula": "32*30",
    "InstallationDateFormula": "cc",
    "ScrappedDateFormula": null,
    "IsDivision43Deduction": "1",
    "HundredPercentOption": 0,
    "NumberOfItems": 1,
    "CanHundredPercent": "0",
    "ExcludeExpenditure": "0",
    "ExcludeFees": "0"
  },
  {
    "ID": 567926,
    "ReportID": 17620,
    "AssetTemplateID": 22,
    "Name": "Air Conditioning - Packaged Unit",
    "Area": 0,
    "IsGivenCost": "0",
    "RateFormula": "75",
    "QuantityFormula": "79",
    "InstallationDateFormula": "cc",
    "ScrappedDateFormula": null,
    "IsDivision43Deduction": "1",
    "HundredPercentOption": 0,
    "NumberOfItems": 1,
    "CanHundredPercent": "0",
    "ExcludeExpenditure": "0",
    "ExcludeFees": "0"
  },
  {
    "ID": 567927,
    "ReportID": 17620,
    "AssetTemplateID": 34,
    "Name": "Bathroom Accessories - Freestanding",
    "Area": 0,
    "IsGivenCost": "0",
    "RateFormula": "200",
    "QuantityFormula": "2",
    "InstallationDateFormula": "cc",
    "ScrappedDateFormula": null,
    "IsDivision43Deduction": "1",
    "HundredPercentOption": 0,
    "NumberOfItems": 1,
    "CanHundredPercent": "0",
    "ExcludeExpenditure": "0",
    "ExcludeFees": "0"
  },
  {
    "ID": 567928,
    "ReportID": 17620,
    "AssetTemplateID": 35,
    "Name": "Blinds",
    "Area": 0,
    "IsGivenCost": "0",
    "RateFormula": "170",
    "QuantityFormula": "79*0.2",
    "InstallationDateFormula": "cc",
    "ScrappedDateFormula": null,
    "IsDivision43Deduction": "1",
    "HundredPercentOption": 0,
    "NumberOfItems": 10,
    "CanHundredPercent": "0",
    "ExcludeExpenditure": "0",
    "ExcludeFees": "0"
  },
  {
    "ID": 567929,
    "ReportID": 17620,
    "AssetTemplateID": 38,
    "Name": "Carpet",
    "Area": 0,
    "IsGivenCost": "0",
    "RateFormula": "90",
    "QuantityFormula": "79*0.4",
    "InstallationDateFormula": "cc",
    "ScrappedDateFormula": null,
    "IsDivision43Deduction": "1",
    "HundredPercentOption": 0,
    "NumberOfItems": 1,
    "CanHundredPercent": "0",
    "ExcludeExpenditure": "0",
    "ExcludeFees": "0"
  },
  {
    "ID": 567931,
    "ReportID": 17620,
    "AssetTemplateID": 46,
    "Name": "Clothes Dryers",
    "Area": 0,
    "IsGivenCost": "0",
    "RateFormula": "900",
    "QuantityFormula": "1",
    "InstallationDateFormula": "cc",
    "ScrappedDateFormula": null,
    "IsDivision43Deduction": "1",
    "HundredPercentOption": 0,
    "NumberOfItems": 1,
    "CanHundredPercent": "0",
    "ExcludeExpenditure": "0",
    "ExcludeFees": "0"
  },
  {
    "ID": 567932,
    "ReportID": 17620,
    "AssetTemplateID": 49,
    "Name": "Cooktops",
    "Area": 0,
    "IsGivenCost": "0",
    "RateFormula": "1595",
    "QuantityFormula": "1",
    "InstallationDateFormula": "cc",
    "ScrappedDateFormula": null,
    "IsDivision43Deduction": "1",
    "HundredPercentOption": 0,
    "NumberOfItems": 1,
    "CanHundredPercent": "0",
    "ExcludeExpenditure": "0",
    "ExcludeFees": "0"
  },
  {
    "ID": 567933,
    "ReportID": 17620,
    "AssetTemplateID": 55,
    "Name": "Dishwashers",
    "Area": 0,
    "IsGivenCost": "0",
    "RateFormula": "1250",
    "QuantityFormula": "1",
    "InstallationDateFormula": "cc",
    "ScrappedDateFormula": null,
    "IsDivision43Deduction": "1",
    "HundredPercentOption": 0,
    "NumberOfItems": 1,
    "CanHundredPercent": "0",
    "ExcludeExpenditure": "0",
    "ExcludeFees": "0"
  },
  {
    "ID": 567934,
    "ReportID": 17620,
    "AssetTemplateID": 56,
    "Name": "Door Closers",
    "Area": 0,
    "IsGivenCost": "0",
    "RateFormula": "150",
    "QuantityFormula": "1",
    "InstallationDateFormula": "cc",
    "ScrappedDateFormula": null,
    "IsDivision43Deduction": "1",
    "HundredPercentOption": 0,
    "NumberOfItems": 1,
    "CanHundredPercent": "0",
    "ExcludeExpenditure": "0",
    "ExcludeFees": "0"
  },
  {
    "ID": 567935,
    "ReportID": 17620,
    "AssetTemplateID": 61,
    "Name": "Exhaust Fans",
    "Area": 0,
    "IsGivenCost": "0",
    "RateFormula": "185",
    "QuantityFormula": "3",
    "InstallationDateFormula": "cc",
    "ScrappedDateFormula": null,
    "IsDivision43Deduction": "1",
    "HundredPercentOption": 0,
    "NumberOfItems": 1,
    "CanHundredPercent": "0",
    "ExcludeExpenditure": "0",
    "ExcludeFees": "0"
  },
  {
    "ID": 567938,
    "ReportID": 17620,
    "AssetTemplateID": 101,
    "Name": "Light Shades",
    "Area": 0,
    "IsGivenCost": "0",
    "RateFormula": "500",
    "QuantityFormula": "2",
    "InstallationDateFormula": "cc",
    "ScrappedDateFormula": null,
    "IsDivision43Deduction": "1",
    "HundredPercentOption": 0,
    "NumberOfItems": 20,
    "CanHundredPercent": "0",
    "ExcludeExpenditure": "0",
    "ExcludeFees": "0"
  },
  {
    "ID": 567939,
    "ReportID": 17620,
    "AssetTemplateID": 108,
    "Name": "Ovens",
    "Area": 0,
    "IsGivenCost": "0",
    "RateFormula": "2450",
    "QuantityFormula": "1",
    "InstallationDateFormula": "cc",
    "ScrappedDateFormula": null,
    "IsDivision43Deduction": "1",
    "HundredPercentOption": 0,
    "NumberOfItems": 1,
    "CanHundredPercent": "0",
    "ExcludeExpenditure": "0",
    "ExcludeFees": "0"
  },
  {
    "ID": 567940,
    "ReportID": 17620,
    "AssetTemplateID": 114,
    "Name": "Rangehoods",
    "Area": 0,
    "IsGivenCost": "0",
    "RateFormula": "995",
    "QuantityFormula": "1",
    "InstallationDateFormula": "cc",
    "ScrappedDateFormula": null,
    "IsDivision43Deduction": "1",
    "HundredPercentOption": 0,
    "NumberOfItems": 1,
    "CanHundredPercent": "0",
    "ExcludeExpenditure": "0",
    "ExcludeFees": "0"
  },
  {
    "ID": 567941,
    "ReportID": 17620,
    "AssetTemplateID": 124,
    "Name": "Smoke Alarms",
    "Area": 0,
    "IsGivenCost": "0",
    "RateFormula": "215",
    "QuantityFormula": "2",
    "InstallationDateFormula": "cc",
    "ScrappedDateFormula": null,
    "IsDivision43Deduction": "1",
    "HundredPercentOption": 0,
    "NumberOfItems": 2,
    "CanHundredPercent": "0",
    "ExcludeExpenditure": "0",
    "ExcludeFees": "0"
  },
  {
    "ID": 567942,
    "ReportID": 17620,
    "AssetTemplateID": 13,
    "Name": "Air Conditioner - Split Systems",
    "Area": 0,
    "IsGivenCost": "0",
    "RateFormula": "2750",
    "QuantityFormula": "2",
    "InstallationDateFormula": "cc",
    "ScrappedDateFormula": null,
    "IsDivision43Deduction": "1",
    "HundredPercentOption": 0,
    "NumberOfItems": 1,
    "CanHundredPercent": "0",
    "ExcludeExpenditure": "0",
    "ExcludeFees": "0"
  },
  {
    "ID": 567943,
    "ReportID": 17620,
    "AssetTemplateID": 155,
    "Name": "Air Conditioner - Split Systems",
    "Area": 1,
    "IsGivenCost": "0",
    "RateFormula": "6000",
    "QuantityFormula": "2",
    "InstallationDateFormula": "cc",
    "ScrappedDateFormula": null,
    "IsDivision43Deduction": "1",
    "HundredPercentOption": 0,
    "NumberOfItems": 1,
    "CanHundredPercent": "0",
    "ExcludeExpenditure": "0",
    "ExcludeFees": "0"
  }
]