[
  {
    "ID": 484223,
    "ReportID": 15117,
    "AssetTemplateID": 13,
    "Name": "Air Conditioner - Split Systems",
    "Area": 0,
    "IsGivenCost": "1",
    "RateFormula": "4500",
    "QuantityFormula": "1",
    "InstallationDateFormula": "cc",
    "ScrappedDateFormula": null,
    "IsDivision43Deduction": "0",
    "HundredPercentOption": 0,
    "NumberOfItems": 3,
    "CanHundredPercent": "0",
    "ExcludeExpenditure": "0",
    "ExcludeFees": "0"
  },
  {
    "ID": 484224,
    "ReportID": 15117,
    "AssetTemplateID": 28,
    "Name": "Automatic Garage Door - Controls",
    "Area": 0,
    "IsGivenCost": "0",
    "RateFormula": "80",
    "QuantityFormula": "2",
    "InstallationDateFormula": "cc",
    "ScrappedDateFormula": null,
    "IsDivision43Deduction": "1",
    "HundredPercentOption": 0,
    "NumberOfItems": 2,
    "CanHundredPercent": "0",
    "ExcludeExpenditure": "0",
    "ExcludeFees": "0"
  },
  {
    "ID": 484225,
    "ReportID": 15117,
    "AssetTemplateID": 29,
    "Name": "Automatic Garage Door - Motors",
    "Area": 0,
    "IsGivenCost": "0",
    "RateFormula": "700",
    "QuantityFormula": "1",
    "InstallationDateFormula": "cc",
    "ScrappedDateFormula": null,
    "IsDivision43Deduction": "1",
    "HundredPercentOption": 0,
    "NumberOfItems": 1,
    "CanHundredPercent": "0",
    "ExcludeExpenditure": "0",
    "ExcludeFees": "0"
  },
  {
    "ID": 484226,
    "ReportID": 15117,
    "AssetTemplateID": 34,
    "Name": "Bathroom Accessories - Freestanding",
    "Area": 0,
    "IsGivenCost": "0",
    "RateFormula": "260",
    "QuantityFormula": "2",
    "InstallationDateFormula": "cc",
    "ScrappedDateFormula": null,
    "IsDivision43Deduction": "1",
    "HundredPercentOption": 0,
    "NumberOfItems": 2,
    "CanHundredPercent": "0",
    "ExcludeExpenditure": "0",
    "ExcludeFees": "0"
  },
  {
    "ID": 484227,
    "ReportID": 15117,
    "AssetTemplateID": 35,
    "Name": "Blinds",
    "Area": 0,
    "IsGivenCost": "0",
    "RateFormula": "165",
    "QuantityFormula": "12",
    "InstallationDateFormula": "cc",
    "ScrappedDateFormula": null,
    "IsDivision43Deduction": "0",
    "HundredPercentOption": 0,
    "NumberOfItems": 10,
    "CanHundredPercent": "0",
    "ExcludeExpenditure": "0",
    "ExcludeFees": "0"
  },
  {
    "ID": 484228,
    "ReportID": 15117,
    "AssetTemplateID": 38,
    "Name": "Carpet",
    "Area": 0,
    "IsGivenCost": "0",
    "RateFormula": "90",
    "QuantityFormula": "35",
    "InstallationDateFormula": "cc",
    "ScrappedDateFormula": null,
    "IsDivision43Deduction": "1",
    "HundredPercentOption": 0,
    "NumberOfItems": 1,
    "CanHundredPercent": "0",
    "ExcludeExpenditure": "0",
    "ExcludeFees": "0"
  },
  {
    "ID": 484229,
    "ReportID": 15117,
    "AssetTemplateID": 39,
    "Name": "Ceiling Fans",
    "Area": 0,
    "IsGivenCost": "0",
    "RateFormula": "350",
    "QuantityFormula": "4",
    "InstallationDateFormula": "cc",
    "ScrappedDateFormula": null,
    "IsDivision43Deduction": "0",
    "HundredPercentOption": 0,
    "NumberOfItems": 3,
    "CanHundredPercent": "0",
    "ExcludeExpenditure": "0",
    "ExcludeFees": "0"
  },
  {
    "ID": 484230,
    "ReportID": 15117,
    "AssetTemplateID": 49,
    "Name": "Cooktops",
    "Area": 0,
    "IsGivenCost": "0",
    "RateFormula": "1255",
    "QuantityFormula": "1",
    "InstallationDateFormula": "cc",
    "ScrappedDateFormula": null,
    "IsDivision43Deduction": "1",
    "HundredPercentOption": 0,
    "NumberOfItems": 1,
    "CanHundredPercent": "0",
    "ExcludeExpenditure": "0",
    "ExcludeFees": "0"
  },
  {
    "ID": 484231,
    "ReportID": 15117,
    "AssetTemplateID": 55,
    "Name": "Dishwashers",
    "Area": 0,
    "IsGivenCost": "0",
    "RateFormula": "1250",
    "QuantityFormula": "1",
    "InstallationDateFormula": "cc",
    "ScrappedDateFormula": null,
    "IsDivision43Deduction": "1",
    "HundredPercentOption": 0,
    "NumberOfItems": 1,
    "CanHundredPercent": "0",
    "ExcludeExpenditure": "0",
    "ExcludeFees": "0"
  },
  {
    "ID": 484233,
    "ReportID": 15117,
    "AssetTemplateID": 61,
    "Name": "Exhaust Fans",
    "Area": 0,
    "IsGivenCost": "0",
    "RateFormula": "185",
    "QuantityFormula": "2",
    "InstallationDateFormula": "cc",
    "ScrappedDateFormula": null,
    "IsDivision43Deduction": "1",
    "HundredPercentOption": 0,
    "NumberOfItems": 1,
    "CanHundredPercent": "0",
    "ExcludeExpenditure": "0",
    "ExcludeFees": "0"
  },
  {
    "ID": 484235,
    "ReportID": 15117,
    "AssetTemplateID": 76,
    "Name": "Garbage Bins",
    "Area": 0,
    "IsGivenCost": "0",
    "RateFormula": "78",
    "QuantityFormula": "3",
    "InstallationDateFormula": "cc",
    "ScrappedDateFormula": null,
    "IsDivision43Deduction": "1",
    "HundredPercentOption": 0,
    "NumberOfItems": 3,
    "CanHundredPercent": "0",
    "ExcludeExpenditure": "0",
    "ExcludeFees": "0"
  },
  {
    "ID": 484236,
    "ReportID": 15117,
    "AssetTemplateID": 92,
    "Name": "Hot Water Systems",
    "Area": 0,
    "IsGivenCost": "0",
    "RateFormula": "1800",
    "QuantityFormula": "1",
    "InstallationDateFormula": "cc",
    "ScrappedDateFormula": null,
    "IsDivision43Deduction": "1",
    "HundredPercentOption": 0,
    "NumberOfItems": 1,
    "CanHundredPercent": "0",
    "ExcludeExpenditure": "0",
    "ExcludeFees": "0"
  },
  {
    "ID": 484237,
    "ReportID": 15117,
    "AssetTemplateID": 100,
    "Name": "Light Fittings - Non Hard Wired",
    "Area": 0,
    "IsGivenCost": "0",
    "RateFormula": "85",
    "QuantityFormula": "26",
    "InstallationDateFormula": "cc",
    "ScrappedDateFormula": null,
    "IsDivision43Deduction": "1",
    "HundredPercentOption": 0,
    "NumberOfItems": 20,
    "CanHundredPercent": "0",
    "ExcludeExpenditure": "0",
    "ExcludeFees": "0"
  },
  {
    "ID": 484238,
    "ReportID": 15117,
    "AssetTemplateID": 101,
    "Name": "Light Shades",
    "Area": 0,
    "IsGivenCost": "1",
    "RateFormula": "687",
    "QuantityFormula": "1",
    "InstallationDateFormula": "cc",
    "ScrappedDateFormula": null,
    "IsDivision43Deduction": "0",
    "HundredPercentOption": 0,
    "NumberOfItems": 20,
    "CanHundredPercent": "0",
    "ExcludeExpenditure": "0",
    "ExcludeFees": "0"
  },
  {
    "ID": 484239,
    "ReportID": 15117,
    "AssetTemplateID": 108,
    "Name": "Ovens",
    "Area": 0,
    "IsGivenCost": "0",
    "RateFormula": "1355",
    "QuantityFormula": "2",
    "InstallationDateFormula": "cc",
    "ScrappedDateFormula": null,
    "IsDivision43Deduction": "1",
    "HundredPercentOption": 0,
    "NumberOfItems": 12,
    "CanHundredPercent": "0",
    "ExcludeExpenditure": "0",
    "ExcludeFees": "0"
  },
  {
    "ID": 484240,
    "ReportID": 15117,
    "AssetTemplateID": 114,
    "Name": "Rangehoods",
    "Area": 0,
    "IsGivenCost": "0",
    "RateFormula": "780",
    "QuantityFormula": "1",
    "InstallationDateFormula": "cc",
    "ScrappedDateFormula": null,
    "IsDivision43Deduction": "1",
    "HundredPercentOption": 0,
    "NumberOfItems": 1,
    "CanHundredPercent": "0",
    "ExcludeExpenditure": "0",
    "ExcludeFees": "0"
  },
  {
    "ID": 484241,
    "ReportID": 15117,
    "AssetTemplateID": 124,
    "Name": "Smoke Alarms",
    "Area": 0,
    "IsGivenCost": "0",
    "RateFormula": "215",
    "QuantityFormula": "3",
    "InstallationDateFormula": "cc",
    "ScrappedDateFormula": null,
    "IsDivision43Deduction": "1",
    "HundredPercentOption": 0,
    "NumberOfItems": 3,
    "CanHundredPercent": "0",
    "ExcludeExpenditure": "0",
    "ExcludeFees": "0"
  },
  {
    "ID": 484422,
    "ReportID": 15117,
    "AssetTemplateID": 52,
    "Name": "Curtains",
    "Area": 0,
    "IsGivenCost": "1",
    "RateFormula": "2143",
    "QuantityFormula": "1",
    "InstallationDateFormula": "cc",
    "ScrappedDateFormula": null,
    "IsDivision43Deduction": "0",
    "HundredPercentOption": 0,
    "NumberOfItems": 10,
    "CanHundredPercent": "0",
    "ExcludeExpenditure": "0",
    "ExcludeFees": "0"
  },
  {
    "ID": 484423,
    "ReportID": 15117,
    "AssetTemplateID": 105,
    "Name": "Microwave Ovens",
    "Area": 0,
    "IsGivenCost": "0",
    "RateFormula": "750",
    "QuantityFormula": "1",
    "InstallationDateFormula": "cc",
    "ScrappedDateFormula": null,
    "IsDivision43Deduction": "1",
    "HundredPercentOption": 0,
    "NumberOfItems": 1,
    "CanHundredPercent": "0",
    "ExcludeExpenditure": "0",
    "ExcludeFees": "0"
  },
  {
    "ID": 484424,
    "ReportID": 15117,
    "AssetTemplateID": 26,
    "Name": "Artificial Grass & Matting",
    "Area": 0,
    "IsGivenCost": "0",
    "RateFormula": "115",
    "QuantityFormula": "2.3*6.2",
    "InstallationDateFormula": "10/12/2015",
    "ScrappedDateFormula": null,
    "IsDivision43Deduction": "1",
    "HundredPercentOption": 0,
    "NumberOfItems": 1,
    "CanHundredPercent": "0",
    "ExcludeExpenditure": "0",
    "ExcludeFees": "0"
  }
]