[
  {
    "ID": 496776,
    "ReportID": 15491,
    "AssetTemplateID": 8,
    "Name": "Garage",
    "Area": 0,
    "IsGivenCost": "0",
    "RateFormula": "1650",
    "QuantityFormula": "35",
    "InstallationDateFormula": "cc",
    "ScrappedDateFormula": null,
    "IsNonDepreciable": "0"
  },
  {
    "ID": 496777,
    "ReportID": 15491,
    "AssetTemplateID": 1,
    "Name": "GFA House",
    "Area": 0,
    "IsGivenCost": "0",
    "RateFormula": "2500",
    "QuantityFormula": "71+19.5+45.5",
    "InstallationDateFormula": "cc",
    "ScrappedDateFormula": null,
    "IsNonDepreciable": "0"
  },
  {
    "ID": 496798,
    "ReportID": 15491,
    "AssetTemplateID": 6,
    "Name": "External",
    "Area": 1,
    "IsGivenCost": "0",
    "RateFormula": "300",
    "QuantityFormula": "2250",
    "InstallationDateFormula": "cc",
    "ScrappedDateFormula": null,
    "IsNonDepreciable": "0"
  },
  {
    "ID": 496804,
    "ReportID": 15491,
    "AssetTemplateID": 11,
    "Name": "Swimming Pool",
    "Area": 1,
    "IsGivenCost": "0",
    "RateFormula": "160000",
    "QuantityFormula": "1",
    "InstallationDateFormula": "cc",
    "ScrappedDateFormula": null,
    "IsNonDepreciable": "0"
  },
  {
    "ID": 496812,
    "ReportID": 15491,
    "AssetTemplateID": 384,
    "Name": "Fencing",
    "Area": 1,
    "IsGivenCost": "0",
    "RateFormula": "250",
    "QuantityFormula": "485",
    "InstallationDateFormula": "cc",
    "ScrappedDateFormula": null,
    "IsNonDepreciable": "0"
  },
  {
    "ID": 496813,
    "ReportID": 15491,
    "AssetTemplateID": 383,
    "Name": "Patio",
    "Area": 0,
    "IsGivenCost": "0",
    "RateFormula": "775",
    "QuantityFormula": "12",
    "InstallationDateFormula": "cc",
    "ScrappedDateFormula": null,
    "IsNonDepreciable": "0"
  }
]