[
  {
    "ID": 512195,
    "ReportID": 15969,
    "AssetTemplateID": 22,
    "Name": "Air Conditioning - Packaged Unit",
    "Area": 0,
    "IsGivenCost": "0",
    "RateFormula": "70",
    "QuantityFormula": "151.61",
    "InstallationDateFormula": "cc",
    "ScrappedDateFormula": null,
    "IsDivision43Deduction": "1",
    "HundredPercentOption": 0,
    "NumberOfItems": 1,
    "CanHundredPercent": "0",
    "ExcludeExpenditure": "0",
    "ExcludeFees": "0"
  },
  {
    "ID": 512196,
    "ReportID": 15969,
    "AssetTemplateID": 28,
    "Name": "Automatic Garage Door - Controls",
    "Area": 0,
    "IsGivenCost": "0",
    "RateFormula": "70",
    "QuantityFormula": "3",
    "InstallationDateFormula": "cc",
    "ScrappedDateFormula": null,
    "IsDivision43Deduction": "1",
    "HundredPercentOption": 0,
    "NumberOfItems": 3,
    "CanHundredPercent": "0",
    "ExcludeExpenditure": "0",
    "ExcludeFees": "0"
  },
  {
    "ID": 512197,
    "ReportID": 15969,
    "AssetTemplateID": 29,
    "Name": "Automatic Garage Door - Motors",
    "Area": 0,
    "IsGivenCost": "0",
    "RateFormula": "650",
    "QuantityFormula": "1",
    "InstallationDateFormula": "cc",
    "ScrappedDateFormula": null,
    "IsDivision43Deduction": "1",
    "HundredPercentOption": 0,
    "NumberOfItems": 1,
    "CanHundredPercent": "0",
    "ExcludeExpenditure": "0",
    "ExcludeFees": "0"
  },
  {
    "ID": 512198,
    "ReportID": 15969,
    "AssetTemplateID": 34,
    "Name": "Bathroom Accessories - Freestanding",
    "Area": 0,
    "IsGivenCost": "0",
    "RateFormula": "260",
    "QuantityFormula": "2",
    "InstallationDateFormula": "cc",
    "ScrappedDateFormula": null,
    "IsDivision43Deduction": "1",
    "HundredPercentOption": 0,
    "NumberOfItems": 1,
    "CanHundredPercent": "0",
    "ExcludeExpenditure": "0",
    "ExcludeFees": "0"
  },
  {
    "ID": 512199,
    "ReportID": 15969,
    "AssetTemplateID": 35,
    "Name": "Blinds",
    "Area": 0,
    "IsGivenCost": "0",
    "RateFormula": "160",
    "QuantityFormula": "0.18*151.61",
    "InstallationDateFormula": "cc",
    "ScrappedDateFormula": null,
    "IsDivision43Deduction": "1",
    "HundredPercentOption": 0,
    "NumberOfItems": 10,
    "CanHundredPercent": "0",
    "ExcludeExpenditure": "0",
    "ExcludeFees": "0"
  },
  {
    "ID": 512200,
    "ReportID": 15969,
    "AssetTemplateID": 38,
    "Name": "Carpet",
    "Area": 0,
    "IsGivenCost": "0",
    "RateFormula": "90",
    "QuantityFormula": "17+10+11+22",
    "InstallationDateFormula": "cc",
    "ScrappedDateFormula": null,
    "IsDivision43Deduction": "1",
    "HundredPercentOption": 0,
    "NumberOfItems": 1,
    "CanHundredPercent": "0",
    "ExcludeExpenditure": "0",
    "ExcludeFees": "0"
  },
  {
    "ID": 512202,
    "ReportID": 15969,
    "AssetTemplateID": 49,
    "Name": "Cooktops",
    "Area": 0,
    "IsGivenCost": "0",
    "RateFormula": "1485",
    "QuantityFormula": "1",
    "InstallationDateFormula": "cc",
    "ScrappedDateFormula": null,
    "IsDivision43Deduction": "1",
    "HundredPercentOption": 0,
    "NumberOfItems": 1,
    "CanHundredPercent": "0",
    "ExcludeExpenditure": "0",
    "ExcludeFees": "0"
  },
  {
    "ID": 512205,
    "ReportID": 15969,
    "AssetTemplateID": 61,
    "Name": "Exhaust Fans",
    "Area": 0,
    "IsGivenCost": "0",
    "RateFormula": "165",
    "QuantityFormula": "3",
    "InstallationDateFormula": "cc",
    "ScrappedDateFormula": null,
    "IsDivision43Deduction": "1",
    "HundredPercentOption": 0,
    "NumberOfItems": 1,
    "CanHundredPercent": "0",
    "ExcludeExpenditure": "0",
    "ExcludeFees": "0"
  },
  {
    "ID": 512206,
    "ReportID": 15969,
    "AssetTemplateID": 68,
    "Name": "Floating Timber Floors",
    "Area": 0,
    "IsGivenCost": "0",
    "RateFormula": "102",
    "QuantityFormula": "59",
    "InstallationDateFormula": "cc",
    "ScrappedDateFormula": null,
    "IsDivision43Deduction": "1",
    "HundredPercentOption": 0,
    "NumberOfItems": 1,
    "CanHundredPercent": "0",
    "ExcludeExpenditure": "0",
    "ExcludeFees": "0"
  },
  {
    "ID": 512207,
    "ReportID": 15969,
    "AssetTemplateID": 76,
    "Name": "Garbage Bins",
    "Area": 0,
    "IsGivenCost": "0",
    "RateFormula": "86",
    "QuantityFormula": "3",
    "InstallationDateFormula": "cc",
    "ScrappedDateFormula": null,
    "IsDivision43Deduction": "1",
    "HundredPercentOption": 0,
    "NumberOfItems": 3,
    "CanHundredPercent": "0",
    "ExcludeExpenditure": "0",
    "ExcludeFees": "0"
  },
  {
    "ID": 512208,
    "ReportID": 15969,
    "AssetTemplateID": 92,
    "Name": "Hot Water Systems",
    "Area": 0,
    "IsGivenCost": "0",
    "RateFormula": "2150",
    "QuantityFormula": "1",
    "InstallationDateFormula": "cc",
    "ScrappedDateFormula": null,
    "IsDivision43Deduction": "1",
    "HundredPercentOption": 0,
    "NumberOfItems": 1,
    "CanHundredPercent": "0",
    "ExcludeExpenditure": "0",
    "ExcludeFees": "0"
  },
  {
    "ID": 512209,
    "ReportID": 15969,
    "AssetTemplateID": 100,
    "Name": "Light Fittings - Non Hard Wired",
    "Area": 0,
    "IsGivenCost": "0",
    "RateFormula": "75",
    "QuantityFormula": "21",
    "InstallationDateFormula": "cc",
    "ScrappedDateFormula": null,
    "IsDivision43Deduction": "1",
    "HundredPercentOption": 0,
    "NumberOfItems": 20,
    "CanHundredPercent": "0",
    "ExcludeExpenditure": "0",
    "ExcludeFees": "0"
  },
  {
    "ID": 512211,
    "ReportID": 15969,
    "AssetTemplateID": 108,
    "Name": "Ovens",
    "Area": 0,
    "IsGivenCost": "0",
    "RateFormula": "2090",
    "QuantityFormula": "1",
    "InstallationDateFormula": "cc",
    "ScrappedDateFormula": null,
    "IsDivision43Deduction": "1",
    "HundredPercentOption": 0,
    "NumberOfItems": 1,
    "CanHundredPercent": "0",
    "ExcludeExpenditure": "0",
    "ExcludeFees": "0"
  },
  {
    "ID": 512212,
    "ReportID": 15969,
    "AssetTemplateID": 114,
    "Name": "Rangehoods",
    "Area": 0,
    "IsGivenCost": "0",
    "RateFormula": "960",
    "QuantityFormula": "1",
    "InstallationDateFormula": "cc",
    "ScrappedDateFormula": null,
    "IsDivision43Deduction": "1",
    "HundredPercentOption": 0,
    "NumberOfItems": 1,
    "CanHundredPercent": "0",
    "ExcludeExpenditure": "0",
    "ExcludeFees": "0"
  },
  {
    "ID": 512213,
    "ReportID": 15969,
    "AssetTemplateID": 124,
    "Name": "Smoke Alarms",
    "Area": 0,
    "IsGivenCost": "0",
    "RateFormula": "185",
    "QuantityFormula": "2",
    "InstallationDateFormula": "cc",
    "ScrappedDateFormula": null,
    "IsDivision43Deduction": "1",
    "HundredPercentOption": 0,
    "NumberOfItems": 2,
    "CanHundredPercent": "0",
    "ExcludeExpenditure": "0",
    "ExcludeFees": "0"
  }
]