[
  {
    "ID": 583762,
    "ReportID": 18114,
    "AssetTemplateID": 13,
    "Name": "Air Conditioner - Split Systems",
    "Area": 0,
    "IsGivenCost": "0",
    "RateFormula": "3333",
    "QuantityFormula": "3",
    "InstallationDateFormula": "cc",
    "ScrappedDateFormula": null,
    "IsDivision43Deduction": "1",
    "HundredPercentOption": 0,
    "NumberOfItems": 1,
    "CanHundredPercent": "0",
    "ExcludeExpenditure": "0",
    "ExcludeFees": "0"
  },
  {
    "ID": 583763,
    "ReportID": 18114,
    "AssetTemplateID": 28,
    "Name": "Automatic Garage Door - Controls",
    "Area": 0,
    "IsGivenCost": "0",
    "RateFormula": "80",
    "QuantityFormula": "2",
    "InstallationDateFormula": "cc",
    "ScrappedDateFormula": null,
    "IsDivision43Deduction": "1",
    "HundredPercentOption": 0,
    "NumberOfItems": 2,
    "CanHundredPercent": "0",
    "ExcludeExpenditure": "0",
    "ExcludeFees": "0"
  },
  {
    "ID": 583764,
    "ReportID": 18114,
    "AssetTemplateID": 29,
    "Name": "Automatic Garage Door - Motors",
    "Area": 0,
    "IsGivenCost": "0",
    "RateFormula": "700",
    "QuantityFormula": "1",
    "InstallationDateFormula": "cc",
    "ScrappedDateFormula": null,
    "IsDivision43Deduction": "1",
    "HundredPercentOption": 0,
    "NumberOfItems": 1,
    "CanHundredPercent": "0",
    "ExcludeExpenditure": "0",
    "ExcludeFees": "0"
  },
  {
    "ID": 583765,
    "ReportID": 18114,
    "AssetTemplateID": 34,
    "Name": "Bathroom Accessories - Freestanding",
    "Area": 0,
    "IsGivenCost": "0",
    "RateFormula": "260",
    "QuantityFormula": "2",
    "InstallationDateFormula": "cc",
    "ScrappedDateFormula": null,
    "IsDivision43Deduction": "1",
    "HundredPercentOption": 0,
    "NumberOfItems": 1,
    "CanHundredPercent": "0",
    "ExcludeExpenditure": "0",
    "ExcludeFees": "0"
  },
  {
    "ID": 583766,
    "ReportID": 18114,
    "AssetTemplateID": 52,
    "Name": "Curtains",
    "Area": 0,
    "IsGivenCost": "0",
    "RateFormula": "110",
    "QuantityFormula": "115*0.2",
    "InstallationDateFormula": "cc",
    "ScrappedDateFormula": null,
    "IsDivision43Deduction": "1",
    "HundredPercentOption": 0,
    "NumberOfItems": 10,
    "CanHundredPercent": "0",
    "ExcludeExpenditure": "0",
    "ExcludeFees": "0"
  },
  {
    "ID": 583767,
    "ReportID": 18114,
    "AssetTemplateID": 38,
    "Name": "Carpet",
    "Area": 0,
    "IsGivenCost": "0",
    "RateFormula": "90",
    "QuantityFormula": "1",
    "InstallationDateFormula": "cc",
    "ScrappedDateFormula": null,
    "IsDivision43Deduction": "1",
    "HundredPercentOption": 0,
    "NumberOfItems": 1,
    "CanHundredPercent": "0",
    "ExcludeExpenditure": "0",
    "ExcludeFees": "0"
  },
  {
    "ID": 583768,
    "ReportID": 18114,
    "AssetTemplateID": 39,
    "Name": "Ceiling Fans",
    "Area": 0,
    "IsGivenCost": "0",
    "RateFormula": "348",
    "QuantityFormula": "4",
    "InstallationDateFormula": "cc",
    "ScrappedDateFormula": null,
    "IsDivision43Deduction": "1",
    "HundredPercentOption": 0,
    "NumberOfItems": 3,
    "CanHundredPercent": "0",
    "ExcludeExpenditure": "0",
    "ExcludeFees": "0"
  },
  {
    "ID": 583769,
    "ReportID": 18114,
    "AssetTemplateID": 49,
    "Name": "Cooktops",
    "Area": 0,
    "IsGivenCost": "0",
    "RateFormula": "1595",
    "QuantityFormula": "1",
    "InstallationDateFormula": "cc",
    "ScrappedDateFormula": null,
    "IsDivision43Deduction": "1",
    "HundredPercentOption": 0,
    "NumberOfItems": 1,
    "CanHundredPercent": "0",
    "ExcludeExpenditure": "0",
    "ExcludeFees": "0"
  },
  {
    "ID": 583770,
    "ReportID": 18114,
    "AssetTemplateID": 55,
    "Name": "Dishwashers",
    "Area": 0,
    "IsGivenCost": "0",
    "RateFormula": "1250",
    "QuantityFormula": "1",
    "InstallationDateFormula": "cc",
    "ScrappedDateFormula": null,
    "IsDivision43Deduction": "1",
    "HundredPercentOption": 0,
    "NumberOfItems": 1,
    "CanHundredPercent": "0",
    "ExcludeExpenditure": "0",
    "ExcludeFees": "0"
  },
  {
    "ID": 583771,
    "ReportID": 18114,
    "AssetTemplateID": 56,
    "Name": "Door Closers",
    "Area": 0,
    "IsGivenCost": "0",
    "RateFormula": "150",
    "QuantityFormula": "3",
    "InstallationDateFormula": "cc",
    "ScrappedDateFormula": null,
    "IsDivision43Deduction": "1",
    "HundredPercentOption": 0,
    "NumberOfItems": 1,
    "CanHundredPercent": "0",
    "ExcludeExpenditure": "0",
    "ExcludeFees": "0"
  },
  {
    "ID": 583772,
    "ReportID": 18114,
    "AssetTemplateID": 61,
    "Name": "Exhaust Fans",
    "Area": 0,
    "IsGivenCost": "0",
    "RateFormula": "185",
    "QuantityFormula": "1",
    "InstallationDateFormula": "cc",
    "ScrappedDateFormula": null,
    "IsDivision43Deduction": "1",
    "HundredPercentOption": 0,
    "NumberOfItems": 1,
    "CanHundredPercent": "0",
    "ExcludeExpenditure": "0",
    "ExcludeFees": "0"
  },
  {
    "ID": 583774,
    "ReportID": 18114,
    "AssetTemplateID": 76,
    "Name": "Garbage Bins",
    "Area": 0,
    "IsGivenCost": "0",
    "RateFormula": "99",
    "QuantityFormula": "3",
    "InstallationDateFormula": "cc",
    "ScrappedDateFormula": null,
    "IsDivision43Deduction": "1",
    "HundredPercentOption": 0,
    "NumberOfItems": 3,
    "CanHundredPercent": "0",
    "ExcludeExpenditure": "0",
    "ExcludeFees": "0"
  },
  {
    "ID": 583775,
    "ReportID": 18114,
    "AssetTemplateID": 92,
    "Name": "Hot Water Systems",
    "Area": 0,
    "IsGivenCost": "0",
    "RateFormula": "2150",
    "QuantityFormula": "1",
    "InstallationDateFormula": "cc",
    "ScrappedDateFormula": null,
    "IsDivision43Deduction": "1",
    "HundredPercentOption": 0,
    "NumberOfItems": 1,
    "CanHundredPercent": "0",
    "ExcludeExpenditure": "0",
    "ExcludeFees": "0"
  },
  {
    "ID": 583777,
    "ReportID": 18114,
    "AssetTemplateID": 101,
    "Name": "Light Shades",
    "Area": 0,
    "IsGivenCost": "0",
    "RateFormula": "155",
    "QuantityFormula": "11",
    "InstallationDateFormula": "cc",
    "ScrappedDateFormula": null,
    "IsDivision43Deduction": "1",
    "HundredPercentOption": 0,
    "NumberOfItems": 20,
    "CanHundredPercent": "0",
    "ExcludeExpenditure": "0",
    "ExcludeFees": "0"
  },
  {
    "ID": 583778,
    "ReportID": 18114,
    "AssetTemplateID": 108,
    "Name": "Ovens",
    "Area": 0,
    "IsGivenCost": "0",
    "RateFormula": "2450",
    "QuantityFormula": "1",
    "InstallationDateFormula": "cc",
    "ScrappedDateFormula": null,
    "IsDivision43Deduction": "1",
    "HundredPercentOption": 0,
    "NumberOfItems": 1,
    "CanHundredPercent": "0",
    "ExcludeExpenditure": "0",
    "ExcludeFees": "0"
  },
  {
    "ID": 583779,
    "ReportID": 18114,
    "AssetTemplateID": 114,
    "Name": "Rangehoods",
    "Area": 0,
    "IsGivenCost": "0",
    "RateFormula": "995",
    "QuantityFormula": "1",
    "InstallationDateFormula": "cc",
    "ScrappedDateFormula": null,
    "IsDivision43Deduction": "1",
    "HundredPercentOption": 0,
    "NumberOfItems": 1,
    "CanHundredPercent": "0",
    "ExcludeExpenditure": "0",
    "ExcludeFees": "0"
  },
  {
    "ID": 583780,
    "ReportID": 18114,
    "AssetTemplateID": 124,
    "Name": "Smoke Alarms",
    "Area": 0,
    "IsGivenCost": "0",
    "RateFormula": "215",
    "QuantityFormula": "3",
    "InstallationDateFormula": "cc",
    "ScrappedDateFormula": null,
    "IsDivision43Deduction": "1",
    "HundredPercentOption": 0,
    "NumberOfItems": 2,
    "CanHundredPercent": "0",
    "ExcludeExpenditure": "0",
    "ExcludeFees": "0"
  }
]