[
  {
    "ID": 568108,
    "ReportID": 17627,
    "AssetTemplateID": 13,
    "Name": "Air Conditioner - Split Systems",
    "Area": 0,
    "IsGivenCost": "0",
    "RateFormula": "2750",
    "QuantityFormula": "5",
    "InstallationDateFormula": "cc",
    "ScrappedDateFormula": null,
    "IsDivision43Deduction": "1",
    "HundredPercentOption": 0,
    "NumberOfItems": 1,
    "CanHundredPercent": "0",
    "ExcludeExpenditure": "0",
    "ExcludeFees": "0"
  },
  {
    "ID": 568109,
    "ReportID": 17627,
    "AssetTemplateID": 28,
    "Name": "Automatic Garage Door - Controls",
    "Area": 0,
    "IsGivenCost": "1",
    "RateFormula": "86",
    "QuantityFormula": "4",
    "InstallationDateFormula": "19/04/2024",
    "ScrappedDateFormula": null,
    "IsDivision43Deduction": "1",
    "HundredPercentOption": 0,
    "NumberOfItems": 2,
    "CanHundredPercent": "0",
    "ExcludeExpenditure": "0",
    "ExcludeFees": "0"
  },
  {
    "ID": 568110,
    "ReportID": 17627,
    "AssetTemplateID": 29,
    "Name": "Automatic Garage Door - Motors",
    "Area": 0,
    "IsGivenCost": "1",
    "RateFormula": "775",
    "QuantityFormula": "2",
    "InstallationDateFormula": "19/04/2024",
    "ScrappedDateFormula": null,
    "IsDivision43Deduction": "1",
    "HundredPercentOption": 0,
    "NumberOfItems": 1,
    "CanHundredPercent": "0",
    "ExcludeExpenditure": "0",
    "ExcludeFees": "0"
  },
  {
    "ID": 568111,
    "ReportID": 17627,
    "AssetTemplateID": 34,
    "Name": "Bathroom Accessories - Freestanding",
    "Area": 0,
    "IsGivenCost": "0",
    "RateFormula": "260",
    "QuantityFormula": "2",
    "InstallationDateFormula": "cc",
    "ScrappedDateFormula": null,
    "IsDivision43Deduction": "1",
    "HundredPercentOption": 0,
    "NumberOfItems": 1,
    "CanHundredPercent": "0",
    "ExcludeExpenditure": "0",
    "ExcludeFees": "0"
  },
  {
    "ID": 568112,
    "ReportID": 17627,
    "AssetTemplateID": 35,
    "Name": "Blinds",
    "Area": 0,
    "IsGivenCost": "0",
    "RateFormula": "170",
    "QuantityFormula": "5",
    "InstallationDateFormula": "cc",
    "ScrappedDateFormula": null,
    "IsDivision43Deduction": "1",
    "HundredPercentOption": 0,
    "NumberOfItems": 10,
    "CanHundredPercent": "0",
    "ExcludeExpenditure": "0",
    "ExcludeFees": "0"
  },
  {
    "ID": 568113,
    "ReportID": 17627,
    "AssetTemplateID": 38,
    "Name": "Carpet",
    "Area": 0,
    "IsGivenCost": "0",
    "RateFormula": "90",
    "QuantityFormula": "41.29",
    "InstallationDateFormula": "cc",
    "ScrappedDateFormula": null,
    "IsDivision43Deduction": "1",
    "HundredPercentOption": 0,
    "NumberOfItems": 1,
    "CanHundredPercent": "0",
    "ExcludeExpenditure": "0",
    "ExcludeFees": "0"
  },
  {
    "ID": 568114,
    "ReportID": 17627,
    "AssetTemplateID": 39,
    "Name": "Ceiling Fans",
    "Area": 0,
    "IsGivenCost": "0",
    "RateFormula": "350",
    "QuantityFormula": "2",
    "InstallationDateFormula": "cc",
    "ScrappedDateFormula": null,
    "IsDivision43Deduction": "1",
    "HundredPercentOption": 0,
    "NumberOfItems": 3,
    "CanHundredPercent": "0",
    "ExcludeExpenditure": "0",
    "ExcludeFees": "0"
  },
  {
    "ID": 568116,
    "ReportID": 17627,
    "AssetTemplateID": 55,
    "Name": "Dishwashers",
    "Area": 0,
    "IsGivenCost": "0",
    "RateFormula": "1250",
    "QuantityFormula": "1",
    "InstallationDateFormula": "cc",
    "ScrappedDateFormula": null,
    "IsDivision43Deduction": "1",
    "HundredPercentOption": 0,
    "NumberOfItems": 1,
    "CanHundredPercent": "0",
    "ExcludeExpenditure": "0",
    "ExcludeFees": "0"
  },
  {
    "ID": 568117,
    "ReportID": 17627,
    "AssetTemplateID": 56,
    "Name": "Door Closers",
    "Area": 0,
    "IsGivenCost": "0",
    "RateFormula": "150",
    "QuantityFormula": "1",
    "InstallationDateFormula": "cc",
    "ScrappedDateFormula": null,
    "IsDivision43Deduction": "1",
    "HundredPercentOption": 0,
    "NumberOfItems": 1,
    "CanHundredPercent": "0",
    "ExcludeExpenditure": "0",
    "ExcludeFees": "0"
  },
  {
    "ID": 568118,
    "ReportID": 17627,
    "AssetTemplateID": 61,
    "Name": "Exhaust Fans",
    "Area": 0,
    "IsGivenCost": "0",
    "RateFormula": "185",
    "QuantityFormula": "3",
    "InstallationDateFormula": "cc",
    "ScrappedDateFormula": null,
    "IsDivision43Deduction": "1",
    "HundredPercentOption": 0,
    "NumberOfItems": 1,
    "CanHundredPercent": "0",
    "ExcludeExpenditure": "0",
    "ExcludeFees": "0"
  },
  {
    "ID": 568119,
    "ReportID": 17627,
    "AssetTemplateID": 68,
    "Name": "Floating Timber Floors",
    "Area": 0,
    "IsGivenCost": "0",
    "RateFormula": "115",
    "QuantityFormula": "97.45",
    "InstallationDateFormula": "cc",
    "ScrappedDateFormula": null,
    "IsDivision43Deduction": "1",
    "HundredPercentOption": 0,
    "NumberOfItems": 1,
    "CanHundredPercent": "0",
    "ExcludeExpenditure": "0",
    "ExcludeFees": "0"
  },
  {
    "ID": 568120,
    "ReportID": 17627,
    "AssetTemplateID": 76,
    "Name": "Garbage Bins",
    "Area": 0,
    "IsGivenCost": "0",
    "RateFormula": "99",
    "QuantityFormula": "3",
    "InstallationDateFormula": "cc",
    "ScrappedDateFormula": null,
    "IsDivision43Deduction": "1",
    "HundredPercentOption": 0,
    "NumberOfItems": 3,
    "CanHundredPercent": "0",
    "ExcludeExpenditure": "0",
    "ExcludeFees": "0"
  },
  {
    "ID": 568121,
    "ReportID": 17627,
    "AssetTemplateID": 92,
    "Name": "Hot Water Systems",
    "Area": 0,
    "IsGivenCost": "0",
    "RateFormula": "2150",
    "QuantityFormula": "1",
    "InstallationDateFormula": "cc",
    "ScrappedDateFormula": null,
    "IsDivision43Deduction": "1",
    "HundredPercentOption": 0,
    "NumberOfItems": 1,
    "CanHundredPercent": "0",
    "ExcludeExpenditure": "0",
    "ExcludeFees": "0"
  },
  {
    "ID": 568122,
    "ReportID": 17627,
    "AssetTemplateID": 100,
    "Name": "Light Fittings - Non Hard Wired",
    "Area": 0,
    "IsGivenCost": "0",
    "RateFormula": "20",
    "QuantityFormula": "33+8",
    "InstallationDateFormula": "cc",
    "ScrappedDateFormula": null,
    "IsDivision43Deduction": "1",
    "HundredPercentOption": 0,
    "NumberOfItems": 20,
    "CanHundredPercent": "0",
    "ExcludeExpenditure": "0",
    "ExcludeFees": "0"
  },
  {
    "ID": 568123,
    "ReportID": 17627,
    "AssetTemplateID": 101,
    "Name": "Light Shades",
    "Area": 0,
    "IsGivenCost": "0",
    "RateFormula": "155",
    "QuantityFormula": "4",
    "InstallationDateFormula": "cc",
    "ScrappedDateFormula": null,
    "IsDivision43Deduction": "1",
    "HundredPercentOption": 0,
    "NumberOfItems": 20,
    "CanHundredPercent": "0",
    "ExcludeExpenditure": "0",
    "ExcludeFees": "0"
  },
  {
    "ID": 568124,
    "ReportID": 17627,
    "AssetTemplateID": 130,
    "Name": "Stoves",
    "Area": 0,
    "IsGivenCost": "0",
    "RateFormula": "2450",
    "QuantityFormula": "1",
    "InstallationDateFormula": "cc",
    "ScrappedDateFormula": null,
    "IsDivision43Deduction": "1",
    "HundredPercentOption": 0,
    "NumberOfItems": 1,
    "CanHundredPercent": "0",
    "ExcludeExpenditure": "0",
    "ExcludeFees": "0"
  },
  {
    "ID": 568125,
    "ReportID": 17627,
    "AssetTemplateID": 114,
    "Name": "Rangehoods",
    "Area": 0,
    "IsGivenCost": "0",
    "RateFormula": "995",
    "QuantityFormula": "1",
    "InstallationDateFormula": "cc",
    "ScrappedDateFormula": null,
    "IsDivision43Deduction": "1",
    "HundredPercentOption": 0,
    "NumberOfItems": 1,
    "CanHundredPercent": "0",
    "ExcludeExpenditure": "0",
    "ExcludeFees": "0"
  },
  {
    "ID": 568126,
    "ReportID": 17627,
    "AssetTemplateID": 124,
    "Name": "Smoke Alarms",
    "Area": 0,
    "IsGivenCost": "0",
    "RateFormula": "215",
    "QuantityFormula": "6",
    "InstallationDateFormula": "cc",
    "ScrappedDateFormula": null,
    "IsDivision43Deduction": "1",
    "HundredPercentOption": 0,
    "NumberOfItems": 2,
    "CanHundredPercent": "0",
    "ExcludeExpenditure": "0",
    "ExcludeFees": "0"
  },
  {
    "ID": 568127,
    "ReportID": 17627,
    "AssetTemplateID": 52,
    "Name": "Curtains",
    "Area": 0,
    "IsGivenCost": "0",
    "RateFormula": "110",
    "QuantityFormula": "66.86",
    "InstallationDateFormula": "cc",
    "ScrappedDateFormula": null,
    "IsDivision43Deduction": "1",
    "HundredPercentOption": 0,
    "NumberOfItems": 10,
    "CanHundredPercent": "0",
    "ExcludeExpenditure": "0",
    "ExcludeFees": "0"
  },
  {
    "ID": 568128,
    "ReportID": 17627,
    "AssetTemplateID": 132,
    "Name": "Swimming Pool - Cleaners",
    "Area": 0,
    "IsGivenCost": "0",
    "RateFormula": "900",
    "QuantityFormula": "1",
    "InstallationDateFormula": "cc",
    "ScrappedDateFormula": null,
    "IsDivision43Deduction": "1",
    "HundredPercentOption": 0,
    "NumberOfItems": 1,
    "CanHundredPercent": "0",
    "ExcludeExpenditure": "0",
    "ExcludeFees": "0"
  },
  {
    "ID": 568129,
    "ReportID": 17627,
    "AssetTemplateID": 133,
    "Name": "Swimming Pool & Spa - Filtration & Chlorinators",
    "Area": 0,
    "IsGivenCost": "0",
    "RateFormula": "3250",
    "QuantityFormula": "1",
    "InstallationDateFormula": "cc",
    "ScrappedDateFormula": null,
    "IsDivision43Deduction": "1",
    "HundredPercentOption": 0,
    "NumberOfItems": 1,
    "CanHundredPercent": "0",
    "ExcludeExpenditure": "0",
    "ExcludeFees": "0"
  },
  {
    "ID": 568130,
    "ReportID": 17627,
    "AssetTemplateID": 125,
    "Name": "Solar Powered Generating System",
    "Area": 0,
    "IsGivenCost": "0",
    "RateFormula": "300",
    "QuantityFormula": "24",
    "InstallationDateFormula": "cc",
    "ScrappedDateFormula": null,
    "IsDivision43Deduction": "1",
    "HundredPercentOption": 0,
    "NumberOfItems": 1,
    "CanHundredPercent": "0",
    "ExcludeExpenditure": "0",
    "ExcludeFees": "0"
  },
  {
    "ID": 568131,
    "ReportID": 17627,
    "AssetTemplateID": 132,
    "Name": "Swimming Pool - Cleaners",
    "Area": 0,
    "IsGivenCost": "1",
    "RateFormula": "1900",
    "QuantityFormula": "1",
    "InstallationDateFormula": "11/02/2025",
    "ScrappedDateFormula": null,
    "IsDivision43Deduction": "0",
    "HundredPercentOption": 0,
    "NumberOfItems": 1,
    "CanHundredPercent": "0",
    "ExcludeExpenditure": "0",
    "ExcludeFees": "0"
  }
]